django_boot_core
tests
