Metadata-Version: 2.1
Name: django-boot-core-starter
Version: 0.2.0
Summary: Django Boot Core Starter
Home-page: https://github.com/django-boot/django-boot-core-starter
Author: Django Boot
Author-email: djangoboot@proton.me
Classifier: Environment :: Web Environment
Classifier: Framework :: Django
Classifier: Framework :: Django :: 4.2
Classifier: Intended Audience :: Developers
Classifier: Operating System :: OS Independent
Classifier: Programming Language :: Python
Classifier: Programming Language :: Python :: 3 :: Only
Classifier: Programming Language :: Python :: 3.9
Classifier: Topic :: Internet :: WWW/HTTP
Requires-Python: >=3.9
License-File: LICENSE
Requires-Dist: Django>=4.2
Requires-Dist: parse-it==2023.10.5.16.31
Requires-Dist: django-boot-rhazes==1.2.0
